LICENSE
MANIFEST.in
README.markdown
setup.cfg
setup.py
cli53/__init__.py
cli53/client.py
cli53.egg-info/PKG-INFO
cli53.egg-info/SOURCES.txt
cli53.egg-info/dependency_links.txt
cli53.egg-info/requires.txt
cli53.egg-info/top_level.txt
scripts/cli53
tests/__init__.py
tests/common.py
tests/test_bind.py
tests/test_commands.py
tests/test_domains.py