Metadata-Version: 1.1
Name: cli53
Version: 0.5.2
Summary: Command line script to administer the Amazon Route 53 DNS service
Home-page: http://loads.pickle.me.uk/cli53/
Author: Barnaby Gray
Author-email: barnaby@pickle.me.uk
License: MIT
Platform: UNKNOWN
Classifier: Development Status :: 3 - Alpha
Classifier: Topic :: Utilities
Classifier: License :: OSI Approved :: MIT License
